mir/ytplay/__init__.py
mir/ytplay/__main__.py
mir.ytplay-0.2.0.dist-info/DESCRIPTION.rst
mir.ytplay-0.2.0.dist-info/METADATA
mir.ytplay-0.2.0.dist-info/RECORD
mir.ytplay-0.2.0.dist-info/WHEEL
mir.ytplay-0.2.0.dist-info/metadata.json
mir.ytplay-0.2.0.dist-info/top_level.txt
