Metadata-Version: 2.0
Name: mir.ytplay
Version: 0.2.0
Summary: Stream music from YouTube.
Home-page: https://github.com/darkfeline/mir.ytplay
Author: Allen Li
Author-email: darkfeline@felesatra.moe
License: UNKNOWN
Platform: UNKNOWN
Classifier: Development Status :: 4 - Beta
Classifier: Intended Audience :: End Users/Desktop
Classifier: License :: OSI Approved :: Apache Software License
Classifier: Programming Language :: Python :: 3.6
